mseep_supercollidermcp-0.1.2.dist-info/licenses/LICENSE
supercollidermcp/__init__.py
supercollidermcp/melody.py
supercollidermcp/osc.py
supercollidermcp/rhythm.py
mseep_supercollidermcp-0.1.2.dist-info/METADATA
mseep_supercollidermcp-0.1.2.dist-info/WHEEL
mseep_supercollidermcp-0.1.2.dist-info/entry_points.txt
mseep_supercollidermcp-0.1.2.dist-info/top_level.txt
mseep_supercollidermcp-0.1.2.dist-info/RECORD
