Metadata-Version: 2.4
Name: mseep-supercollidermcp
Version: 0.1.2
Summary: MCP server for SuperCollider with OSC communication
Home-page: 
Author: mseep
Author-email: mseep <support@skydeck.ai>
Maintainer-email: mseep <support@skydeck.ai>
Requires-Python: >=3.6
License-File: LICENSE
Requires-Dist: mcp[cli]>=1.6.0
Requires-Dist: python-osc>=1.9.3
Dynamic: author
Dynamic: license-file
Dynamic: requires-python
